vi_rag/__init__.py
vi_rag/core.py
vi_rag/py.typed
vi_rag/utils.py
vi_rag/config/__init__.py
vi_rag/config/settings.py
vi_rag/core/__init__.py
vi_rag/core/document.py
vi_rag/ingestion/__init__.py
vi_rag/ingestion/chunker.py
vi_rag/ingestion/loader.py
vi_rag/ingestion/splitter.py
vi_rag/models/__init__.py
vi_rag/models/embedding.py
vi_rag/models/gemini_llm.py
vi_rag/models/prompt.py
vi_rag/plugin/__init__.py
vi_rag/retrieval/__init__.py
vi_rag/retrieval/bm25_index.py
vi_rag/retrieval/docstore.py
vi_rag/retrieval/hybrid_retrie.py
vi_rag/retrieval/parent_child_retriever.py
vi_rag/retrieval/qdrant.py
vi_rag/retrieval/rag_engine.py
vi_rag/retrieval/reranker.py
vi_rag/retrieval/retriever.py
vi_rag-0.1.4.dist-info/licenses/LICENSE
vi_rag-0.1.4.dist-info/METADATA
vi_rag-0.1.4.dist-info/WHEEL
vi_rag-0.1.4.dist-info/top_level.txt
vi_rag-0.1.4.dist-info/RECORD
