Metadata-Version: 2.4
Name: vi-rag
Version: 0.1.4
Summary: Vietnamese Retrieval-Augmented Generation (RAG) Framework
Author-email: Vi-RAG Team <virag@example.com>
Project-URL: Homepage, https://github.com/NOT-erorr/PBL_2025_Vi-RAG_framework
Project-URL: Repository, https://github.com/NOT-erorr/PBL_2025_Vi-RAG_framework
Project-URL: Documentation, https://github.com/NOT-erorr/PBL_2025_Vi-RAG_framework/blob/main/README.md
Project-URL: Bug Tracker, https://github.com/NOT-erorr/PBL_2025_Vi-RAG_framework/issues
Keywords: rag,retrieval-augmented-generation,vietnamese-nlp,document-processing,vector-search,gemini,qdrant
Classifier: Development Status :: 3 - Alpha
Classifier: Intended Audience :: Developers
Classifier: Intended Audience :: Science/Research
Classifier: License :: OSI Approved :: MIT License
Classifier: Programming Language :: Python :: 3
Classifier: Programming Language :: Python :: 3.8
Classifier: Programming Language :: Python :: 3.9
Classifier: Programming Language :: Python :: 3.10
Classifier: Programming Language :: Python :: 3.11
Classifier: Programming Language :: Python :: 3.12
Classifier: Topic :: Scientific/Engineering :: Artificial Intelligence
Classifier: Topic :: Text Processing :: Linguistic
Requires-Python: >=3.8
License-File: LICENSE
Requires-Dist: numpy<3.0.0,>=1.21.0
Requires-Dist: python-dotenv>=0.19.0
Requires-Dist: pypdf>=3.0.0
Requires-Dist: python-docx>=0.8.11
Requires-Dist: underthesea>=6.0.0
Requires-Dist: qdrant-client>=1.7.0
Requires-Dist: google-genai>=0.1.0
Requires-Dist: sentence-transformers>=2.0.0
Provides-Extra: dev
Requires-Dist: pytest>=7.0.0; extra == "dev"
Requires-Dist: pytest-cov>=4.0.0; extra == "dev"
Requires-Dist: black>=23.0.0; extra == "dev"
Requires-Dist: isort>=5.12.0; extra == "dev"
Requires-Dist: flake8>=6.0.0; extra == "dev"
Requires-Dist: mypy>=1.0.0; extra == "dev"
Provides-Extra: evaluation
Requires-Dist: ragas>=0.4.0; extra == "evaluation"
Requires-Dist: datasets>=4.0.0; extra == "evaluation"
Provides-Extra: all
Requires-Dist: vi-rag[dev,evaluation]; extra == "all"
Dynamic: license-file
